LICENSE
README.md
setup.cfg
setup.py
autocomplete/__init__.py
autocomplete/create_dataset.py
autocomplete/gpt2_coder.py
autocomplete/server.py
autocomplete/source_code_dataset.md
autocomplete/upload_dataset.py
code_autocomplete.egg-info/PKG-INFO
code_autocomplete.egg-info/SOURCES.txt
code_autocomplete.egg-info/dependency_links.txt
code_autocomplete.egg-info/not-zip-safe
code_autocomplete.egg-info/requires.txt
code_autocomplete.egg-info/top_level.txt