Metadata-Version: 2.1
Name: code-autocomplete
Version: 0.0.4
Summary: Code AutoComplete
Home-page: https://github.com/shibing624/code-autocomplete
Author: XuMing
Author-email: xuming624@qq.com
License: Apache License 2.0
Keywords: autocomplete,code-autocomplete
Platform: UNKNOWN
Classifier: Intended Audience :: Developers
Classifier: Operating System :: OS Independent
Classifier: Natural Language :: Chinese (Simplified)
Classifier: Natural Language :: Chinese (Traditional)
Classifier: Programming Language :: Python
Classifier: Programming Language :: Python :: 3
Classifier: Topic :: Text Processing
Classifier: Topic :: Text Processing :: Indexing
Classifier: Topic :: Text Processing :: Linguistic
Requires-Python: >=3.5
